{
  "url": "https://cats.lilly.com/guide/GitHubRepos",
  "title": "**GitHub** | CATS",
  "description": "The source code for CATS is spanned across multiple GitHub repositories. Check out the list of repositories here.",
  "h1": [
    "GitHub"
  ],
  "h2": [
    "Application Deployment Repos​",
    "Platform Infrastructure Repos​"
  ],
  "h3": [],
  "text_content": "**GitHub** | CATS\nSkip to main content\n🚀\nComing Soon: Hangar!\nWe are merging Lilly Kubed and CATS into a single, streamlined platform:\nHangar\n. Stay tuned for updates!\nCATS Docs\nGuide\nCATS Agent\nCATSbot\nSubmit A Ticket\nStack Overflow\nPRD env\nQA env\nDEV env\nSearch\n⌘\nK\nWhat Is CATS?\nIntroduction\nPlatform Overview\nShared Responsibility Model\nGitHub repositories\nGitHub Teams\nCATS Platform Agent\nCATSbot Virtual Assistant\nNews\nJump Start\nK8s Configuration\nDashboard Offerings\nUsing AWS Services\nObservability\nSystem Services\nArchitecture\nSupport\nAdmin\nWhat Is CATS?\nGitHub repositories\nOn this page\nGitHub\nThe source code for CATS is spanned across multiple GitHub repositories. Check out the list of repositories\nhere.\nAccess is controlled through GitHub Team memberships.  See\nhttps://github.com/EliLillyCo/LRL_light_k8s_infra_apps_docs/blob/main/docs/guide/GitHubTeams.md\nfor more details.\nApplication Deployment Repos\n​\nEnvironment\nRepository\nDescription\nDevelopment\nLRL_light_k8s_infra_apps_test\nApplication deployment repo that allows customers to deploy their solutions into our Dev Cluster\nQA\nLRL_light_k8s_infra_apps_qa\nApplication deployment repo that allows customers to deploy their solutions into our QA Cluster\nProduction\nLRL_light_k8s_infra_apps\nApplication deployment repo that allows customers to deploy their solutions into our PRD Cluster\nPlatform Infrastructure Repos\n​\nThe following list of github repositories contain parts of the CATS infrastructure in some way or another.\nRepository URL\nDescription\nLRL_light_k8s_infra\nMain infrastructure code for CATS\n. Largest repo that majority of source code is housed in. Likely references other repos with smaller components.\nLRL_light_k8s_infra_apps_docs\nContains the source code for this Docs Site!\nLRL_light_k8s_infra_CATSbot\nThis repository contains automation that periodically retrains the CatsBot using updated content from the Cats Documentation Repository. By continuously aligning with the latest changes on the documentation site, the bot is able to provide users with accurate and current information.\nLRL_light_k8s_infra_app_client_python\nPython-based client libraries for interacting with Kubernetes apps in the Light infra.\nLRL_light_k8s_infra_app_client_r\nR-based client libraries for Kubernetes applications on the Light infrastructure.\nLRL_light_k8s_infra_apps_validator\nWill contain tools and automation scripts designed to validate applications within the Light Kubernetes infrastructure. This validation process includes automated tests, configuration checks, and compliance verifications, ensuring each application meets the required standards before deployment. By continuously monitoring and validating applications, this repository helps maintain quality, stability, and compliance across the Kubernetes environment. In Development still.\nLRL_light_k8s_infra_go_bouncer\nBouncer is an authorization service that uses Microsoft Graph & K8s to provide easy authorization for microservice applications. This version is written in GO.\nLRL_light_k8s_infra_bouncer\nDeprecated - Original Bouncer Service that handled authentication services for the cluster\nLRL_light_k8s_infra_credential_service\nThis repo contains a simple service designed to be deployed as a K8s cron job that periodically pushes ECR temporary docker credentials to the github actions secret store.\nLRL_light_k8s_infra_echo\nThis repo contains RESTFUL API's to check networking inside of a k8s pod\nLRL_light_k8s_infra_healthcheck\nHealth-check service for monitoring CATS Kubernetes infrastructure status.\nLRL_light_k8s_infra_manager\nThis project manages the Light K8s custom infrastructure resources. This includes managing syncing AppRunner with the cluster ingress for external access, managing compute profiles per annotations on the namespace object, and provisioning roles in AWS with connection to k8s.\nspe-platforms-agent\nThis repo contains the source code for the CATS Platform Agent toolkit server\nLRL_cats_argocd_test\nTest configurations for deploying applications using ArgoCD in the CATS environment.\nLRL_eks_cert_manager\ncert-manager is a Kubernetes addon to automate the management and issuance of TLS certificates from various issuing sources. It will ensure certificates are valid and up to date periodically, and attempt to renew certificates at an appropriate time before expiry.\nLRL_light_aws-smtp-relay\nSMTP server to relay emails via Amazon SES or Amazon Pinpoint using IAM roles.\nLRL_light_livedesign\nThis repository contains the CDK stacks to deploy livedesign AWS infrastructure\nLRL_light_omics_docs\nDocumentation and resources for the Omics solution.\nLRL_light_security\nThis repository contains python automation code to create LIGHT security controlls. The automation is designed to be idempotent. It will always try to make the AWS Account where it's run match the data domain definitions defined in the repository.\nLRL_light_traefik-forward-auth\nA minimal forward authentication service that provides OAuth/SSO login and authentication for the traefik reverse proxy/load balancer.\naws-efs-csi-pv-provisioner\nKubernetes CSI driver to dynamically provisions Persistent Volumes (PVs) in response to user-requested Persistent Volume Clains (PVCs). Each PV / PVC is a subdirectory on a single, cluster-wide EFS file system. Works in conjunction with the AWS EFS CSI driver.\naws-fsx-ontap-configs\nMaintain the CF and other configurations for Amazon FSX for ONTAP\ncrossplane\nCrossplane configurations for managing cloud-native Kubernetes resources.\ncrossplane-contrib_provider-aws\nThis provider-aws repository is the Crossplane infrastructure provider for Amazon Web Services (AWS). The provider that is built from the source code in this repository can be installed into a Crossplane control plane\neks-charts\nHelm charts for deploying resources and services on AWS EKS.\nflux\nFlux GitOps configurations for Kubernetes clusters.\nfluxcd-community_helm-charts\nCommunity-contributed Helm charts for FluxCD deployments.\nfluxcd_flux2\nFlux v2 configurations and controllers for GitOps deployments in Kubernetes.\nfluxcd_helm-controller\nHelm controller for FluxCD to manage Helm releases in GitOps workflows.\nfluxcd_image-automation-controller\nFluxCD controller for automating container image updates.\nfluxcd_image-reflector-controller\nReflects container image metadata for FluxCD automation.\nfluxcd_notification-controller\nNotification controller for alerting and event-based actions in FluxCD.\ngrafana-helm-charts\nHelm charts for deploying and configuring Grafana in Kubernetes.\nkedacore-charts\nHelm charts for KEDA, an event-driven autoscaler for Kubernetes.\nlrl-aws-tools\nStandard docker tools for AWS & K8s. Collection of AWS tools and utilities used within the LRL infrastructure.\nlrl-cloud-browser\nThis repository contains the API and web application for browsing cloud object stores.\nlrl-cloud-browser-1\nDeprecated - Legacy version of the LRL cloud resource browser.\nlrl-cloud-patterns\nThis repository is designed to provide guides, templates, and code samples for common cloud patterns in Lilly RIDS.\nlrl-cluwe-cli-api-solutions\nthis repository use to keep api for fsx api via cli access.\nlrl-pgadmin\nThis repo contains code that extends PG Admin server to securly auto refresh database credentials from a kubernetes environment scoped to named users. This allows secure remote access to postgresql databases isolated in a kubernetes cluster deployment.\nprometheus-community-helm-charts\nHelm charts for Prometheus monitoring systems.\nFairwindsOps/gemini\nGemini is a Kubernetes CRD and operator for managing VolumeSnapshots. This allows you to create a snapshot of the data on your PersistentVolumes on a regular schedule, retire old snapshots, and restore snapshots with minimal downtime.\nrds_database_creation\nThis repository contains information on the process as well as the CloudFormation template that is required when restoring a relational database from a backup or a snapshot. This template can also be used for the initial RDS setup. Please note that this would be independent of your application CI/CD pipeline and would only be used for either creating a new DB instance or restoring an RDS instance from snapshot.\nelastic_cloud-on-k8s\nElasticsearch\ncert-manager_cert-manager\nNew Cert Manager\ngrafana_mimir?tab=readme-ov-file\nMimir\njaeger_helm-charts\nJaeger\ngrafana-helm-charts/commits/main/\nPromtail + Loki (Old Grafana Helm)\nEdit this page\nPrevious\nShared Responsibility Model\nNext\nGitHub Teams\nApplication Deployment Repos\nPlatform Infrastructure Repos\nLilly SPE Research Technology and Platforms",
  "links_found": 0,
  "depth": 1,
  "crawled_at": "2026-03-20T14:57:03.152883",
  "pagination_items": [
    {
      "tab": "default",
      "content": {
        "title": "GitHub",
        "description": "The source code for CATS is spanned across multiple GitHub repositories. Check out the list of repositorieshere.",
        "links": [
          "/",
          "https://github.com/orgs/EliLillyCo/teams/lrl_light_k8s_infra_write/repositories",
          "https://github.com/EliLillyCo/LRL_light_k8s_infra_apps_docs/blob/main/docs/guide/GitHubTeams.md",
          "#application-deployment-repos",
          "https://github.com/EliLillyCo/LRL_light_k8s_infra_apps_test",
          "https://github.com/EliLillyCo/LRL_light_k8s_infra_apps_qa",
          "https://github.com/EliLillyCo/LRL_light_k8s_infra_apps",
          "#platform-infrastructure-repos",
          "https://github.com/EliLillyCo/LRL_light_k8s_infra",
          "https://github.com/EliLillyCo/LRL_light_k8s_infra_apps_docs",
          "https://github.com/EliLillyCo/LRL_light_k8s_infra_CATSbot",
          "https://github.com/EliLillyCo/LRL_light_k8s_infra_app_client_python",
          "https://github.com/EliLillyCo/LRL_light_k8s_infra_app_client_r",
          "https://github.com/EliLillyCo/LRL_light_k8s_infra_apps_validator",
          "https://github.com/EliLillyCo/LRL_light_k8s_infra_go_bouncer",
          "https://github.com/EliLillyCo/LRL_light_k8s_infra_bouncer",
          "https://github.com/EliLillyCo/LRL_light_k8s_infra_credential_service",
          "https://github.com/EliLillyCo/LRL_light_k8s_infra_echo",
          "https://github.com/EliLillyCo/LRL_light_k8s_infra_healthcheck",
          "https://github.com/EliLillyCo/LRL_light_k8s_infra_manager",
          "https://github.com/EliLillyCo/spe-platforms-agent",
          "https://github.com/EliLillyCo/LRL_cats_argocd_test",
          "https://github.com/EliLillyCo/LRL_eks_cert_manager",
          "https://github.com/EliLillyCo/LRL_light_aws-smtp-relay",
          "https://github.com/EliLillyCo/LRL_light_livedesign",
          "https://github.com/EliLillyCo/LRL_light_omics_docs",
          "https://github.com/EliLillyCo/LRL_light_security",
          "https://github.com/EliLillyCo/LRL_light_traefik-forward-auth",
          "https://github.com/EliLillyCo/aws-efs-csi-pv-provisioner",
          "https://github.com/EliLillyCo/aws-fsx-ontap-configs",
          "https://github.com/EliLillyCo/crossplane",
          "https://github.com/EliLillyCo/crossplane-contrib_provider-aws",
          "https://github.com/EliLillyCo/eks-charts",
          "https://github.com/EliLillyCo/flux",
          "https://github.com/EliLillyCo/fluxcd-community_helm-charts",
          "https://github.com/EliLillyCo/fluxcd_flux2",
          "https://github.com/EliLillyCo/fluxcd_helm-controller",
          "https://github.com/EliLillyCo/fluxcd_image-automation-controller",
          "https://github.com/EliLillyCo/fluxcd_image-reflector-controller",
          "https://github.com/EliLillyCo/fluxcd_notification-controller",
          "https://github.com/EliLillyCo/grafana-helm-charts",
          "https://github.com/EliLillyCo/kedacore-charts",
          "https://github.com/EliLillyCo/lrl-aws-tools",
          "https://github.com/EliLillyCo/lrl-cloud-browser",
          "https://github.com/EliLillyCo/lrl-cloud-browser-1",
          "https://github.com/EliLillyCo/lrl-cloud-patterns",
          "https://github.com/EliLillyCo/lrl-cluwe-cli-api-solutions",
          "https://github.com/EliLillyCo/lrl-pgadmin",
          "https://github.com/EliLillyCo/prometheus-community-helm-charts",
          "https://github.com/FairwindsOps/gemini",
          "https://github.com/EliLillyCo/rds_database_creation",
          "https://github.com/EliLillyCo/elastic_cloud-on-k8s",
          "https://github.com/EliLillyCo/cert-manager_cert-manager",
          "https://github.com/EliLillyCo/grafana_mimir?tab=readme-ov-file",
          "https://github.com/EliLillyCo/jaeger_helm-charts",
          "https://github.com/EliLillyCo/grafana-helm-charts/commits/main/",
          "https://github.com/EliLillyCo/LRL_light_k8s_infra_apps_docs/tree/main/docs/guide/GitHubRepos.md"
        ]
      }
    }
  ],
  "pagination_count": 1
}