{
  "url": "https://cats.lilly.com/guide/ComputeAndWorkloadScheduling",
  "title": "Compute and Workload Scheduling | CATS",
  "description": "There are three types of provisioned nodes supported by the platform:",
  "h1": [
    "Compute and Workload Scheduling"
  ],
  "h2": [
    "Services that Schedule Workloads​",
    "Node Networking Configurations​",
    "Configuration Options​",
    "Examples​",
    "Namespace Configuration​",
    "Scheduling Workloads​"
  ],
  "h3": [
    "Fargate (planned for obsolescence in 2025)​",
    "EC2 Autoscaling Groups and Managed EKS NodeGroups​",
    "AWS Karpenter​",
    "On-premise Network Connected Nodes​",
    "Configure Workload Scheduling via Namespace Annotation​",
    "Affinities, Selectors, Tolerations, and Topologies, \"Oh My!\"​",
    "Karpenter​",
    "Fargate Only Namespace (serverlessnamespace)​",
    "EC2 or Fargate Namespace (hybridnamespace)​",
    "Deployment Scheduled on Fargate inserverlessNamespace​",
    "Deployment Scheduled on Fargate inhybridNamespace​",
    "Deployment Scheduled on Default EC2 inhybridNamespace​",
    "Deployment Scheduled on Default On-premise Connected EC2 inhybridNamespace​",
    "Deployment Scheduled on Custom Dedicated EC2 Instance​"
  ],
  "text_content": "Compute and Workload Scheduling | CATS\nSkip to main content\n🚀\nComing Soon: Hangar!\nWe are merging Lilly Kubed and CATS into a single, streamlined platform:\nHangar\n. Stay tuned for updates!\nCATS Docs\nGuide\nCATS Agent\nCATSbot\nSubmit A Ticket\nStack Overflow\nPRD env\nQA env\nDEV env\nSearch\n⌘\nK\nWhat Is CATS?\nIntroduction\nPlatform Overview\nShared Responsibility Model\nGitHub repositories\nGitHub Teams\nCATS Platform Agent\nCATSbot Virtual Assistant\nNews\nJump Start\nK8s Configuration\nOverview\nNamespace\nDeployment\nService\nIngress\nIngress Patterns\nCompute and Workload Scheduling\nScaling\nStorage\nCronJob\nJobs\nRate Limit\nExternal Secrets\nHelmRelease\nExternal Integrations\nGraph User Info\nMakefile\nVelero Backups\nRDS Database Restore\nNamespace Decommission\nS3 Lifecycle Tagging\nDashboard Offerings\nUsing AWS Services\nObservability\nSystem Services\nArchitecture\nSupport\nAdmin\nK8s Configuration\nCompute and Workload Scheduling\nOn this page\nCompute and Workload Scheduling\nThere are three types of provisioned nodes supported by the platform:\nFargate (serverless) nodes\nNodes via EC2 Autoscaling Groups\nNodes via AWS Karpenter\nServices that Schedule Workloads\n​\nFargate (planned for obsolescence in 2025)\n​\nFargate has been the main provisioned node kind since the first release of CATS. It supports a configurable array of compute types\nshown here\n, and scales relatively well for many workloads. These nodes are managed by AWS and the CATS platform is unable to support many new upcoming services as the control of the nodes themselves are not fully available to our team. As the platform continues to expand its adoption of the AWS Karpenter node scheduler, the usage of Fargate will be reduced and eventually replaced over time.\nEC2 Autoscaling Groups and Managed EKS NodeGroups\n​\nThese node schedulers leverage EC2 Autoscaling Groups to provision EC2 instances that are joined to the CATS cluster. This pattern was suggested for custom EC2 node configuration from the beginning of the CATS platform through 2024. This method of provisioning compute has been mainly replaced by the features of AWS Karpenter, and existing use cases will be shifted to AWS Karpenter over time. For an up-to-date list of existing configurations, please see our infra code repo here:\nClick here\nAWS Karpenter\n​\nThis node scheduling technology will be leveraged in Q4 2024 onward and provides a comprehensive and robust scheduling tool for nodes. This is the preferred mechanism for custom nodes for application teams and additional information can be found in our\nAWS Karpenter documentation\n. The CATS platform is in an early phase of its adoption of Karpenter and does not currently support automation to enable Karpenter for scheduling. Guidance for scheduling is provided on this page in the examples.\nNode Networking Configurations\n​\nOn-premise Network Connected Nodes\n​\nWhen using this method to schedule pods, the pods themselves are not hosted on-premises but this method facilitates connections to on-prem hosted services and/or databases.\nIn addition to implementing the below template, please ensure that the\ncompute\nannotation on your namespace is set to\nhybrid\n. See further details on how to do implement this configuration change\nhere\n.\nBy scheduling your pod on the OnPremis node group your security policy will NOT be the default security group sg-main. Instead your pod will be a part of the sg-onprem security group. further details about these security groups and their differences can be found\nhere\n.\nWhen a pod is scheduled on the onPrem nodegroup you cannot directly talk to other resources deployed on the CATS Platform. This was a trade off we had to make to comply with security requirmeents. Please see the below diagram to better undertand how you may want to talk with other resources in your namespace.\nConfiguration Options\n​\nConfigure Workload Scheduling via Namespace Annotation\n​\nTo configure your namespace to use Fargate / EC2 instances, you must place the annotation:\napp.lrl.lilly.com/compute\nwith a value of either\nserverless\nto allow using only Fargate OR\nhybrid\nto allow using both EC2 or Fargate.  NOTE: If you chose\nhybrid\nyou must label your containers to allow them to run on Fargate, while if you chose\nserverless\nall your containers will run on Fargate without special config.\nNOTE on AWS Karpenter Scheduling: this feature does not automatically schedule workloads to AWS Karpenter nodes. In order to schedule to AWS Karpenter nodes, the\nhybrid\noption must be selected.\nAffinities, Selectors, Tolerations, and Topologies, \"Oh My!\"\n​\nThe Kubernetes development team provides rich documentation around concepts for workload scheduling. The CATS team does not provide active consulting or training related to leveraging these features, and it is expected that application teams wanting to use scheduling features educate themselves scheduling techniques by reading the docs posted here:\nAssigning Pods to Nodes\nprovides information on\nnodeSelector\nusage\nprovides information on\naffinity\nand\n*AntiAffinity\nusage\nTaints and Tolerations\nprovides information on node\ntaints\nused to constrain scheduling and execution\nprovides information on\ntolerations\nused to accept node\ntaints\nExamples\n​\nKarpenter\n​\nDeployment Scheduled on General-Purpose Node\n​\nNote that a combination of spec.nodeSelector and spec.tolerations for the Pod template is required for scheduling. Example application running on EC2 within a hybrid namespace:\napiVersion\n:\napps/v1\nkind\n:\nDeployment\nmetadata\n:\nname\n:\nyour\n-\napp\nnamespace\n:\nyour\n-\napp\n-\nnamespace\n-\ndev\nspec\n:\nselector\n:\nmatchLabels\n:\napp.kubernetes.io/name\n:\nyour\n-\napp\ntemplate\n:\nmetadata\n:\nlabels\n:\napp.kubernetes.io/name\n:\nyour\n-\napp\nspec\n:\ncontainers\n:\n-\nimage\n:\n283234040926.dkr.ecr.us\n-\neast\n-\n2.amazonaws.com/lrl_new_app\n:\nsha\n-\na431842\n# {\"$imagepolicy\": \"<namespace-name>:<policy-name>\"}\nname\n:\nyour\n-\napp\nresources\n:\nlimits\n:\ncpu\n:\n3\nmemory\n:\n40G\nrequests\n:\ncpu\n:\n3\nmemory\n:\n40G\nports\n:\n-\ncontainerPort\n:\n3838\n# Use node selector to specify the run environment (dev/qa/prd)\nnodeSelector\n:\napp.lilly.com/env\n:\n[\ndev\n|\nqa\n|\nprd\n]\n# **NOTE: this is different from the older `app.lrl.lilly.com/env: [dev|qa|prd]` nodeSelector label key!**\napp.lilly.com/node-kind\n:\ngeneral\n-\npurpose\ntolerations\n:\n-\nkey\n:\napp.lilly.com/env\nvalue\n:\n\"[dev|qa|prd]\"\neffect\n:\n\"NoSchedule\"\nDeployment Scheduled on Accelerated (GPU-enabled) Node\n​\nNote that a combination of spec.nodeSelector and spec.tolerations for the Pod template is required for scheduling. Example application running on EC2 within a hybrid namespace:\napiVersion\n:\napps/v1\nkind\n:\nDeployment\nmetadata\n:\nname\n:\nyour\n-\napp\nnamespace\n:\nyour\n-\napp\n-\nnamespace\n-\ndev\nspec\n:\nselector\n:\nmatchLabels\n:\napp.kubernetes.io/name\n:\nyour\n-\napp\ntemplate\n:\nmetadata\n:\nlabels\n:\napp.kubernetes.io/name\n:\nyour\n-\napp\nspec\n:\ncontainers\n:\n-\nimage\n:\n283234040926.dkr.ecr.us\n-\neast\n-\n2.amazonaws.com/lrl_new_app\n:\nsha\n-\na431842\n# {\"$imagepolicy\": \"<namespace-name>:<policy-name>\"}\nname\n:\nyour\n-\napp\nresources\n:\nlimits\n:\ncpu\n:\n3\nmemory\n:\n40G\nrequests\n:\ncpu\n:\n3\nmemory\n:\n40G\nports\n:\n-\ncontainerPort\n:\n3838\n# Use node selector to specify the run environment (dev/qa/prd)\nnodeSelector\n:\napp.lilly.com/env\n:\n[\ndev\n|\nqa\n|\nprd\n]\n# **NOTE: this is different from the older `app.lrl.lilly.com/env: [dev|qa|prd]` nodeSelector label key!**\napp.lilly.com/node-kind\n:\naccelerated\ntolerations\n:\n-\nkey\n:\napp.lilly.com/env\nvalue\n:\n\"[dev|qa|prd]\"\neffect\n:\n\"NoSchedule\"\n-\nkey\n:\nnvidia.com/gpu\nvalue\n:\n\"true\"\neffect\n:\n\"NoSchedule\"\nNamespace Configuration\n​\nFargate Only Namespace (\nserverless\nnamespace)\n​\nNote the\napp.lrl.lilly.com/compute: serverless\nannotation on the namespace.\napiVersion\n:\nv1\nkind\n:\nNamespace\nmetadata\n:\nname\n:\nyour\n-\napp\n-\nnamespace\n-\ndev\nlabels\n:\ncost-center\n:\nyour\n-\napps\n-\ncost\n-\ncenter\n-\nid\nannotations\n:\napp.lrl.lilly.com/compute\n:\nserverless\nEC2 or Fargate Namespace (\nhybrid\nnamespace)\n​\nNote the\napp.lrl.lilly.com/compute: hybrid\ntag on the namespace annotation. The\napp.lrl.lilly.com/compute: serverless\nmetadata.label for the Pod template will be required for workloads defined in this particular namespace to use Fargate.\napiVersion\n:\nv1\nkind\n:\nNamespace\nmetadata\n:\nname\n:\nyour\n-\napp\n-\nnamespace\n-\ndev\nlabels\n:\ncost-center\n:\nyour\n-\napps\n-\ncost\n-\ncenter\n-\nid\nannotations\n:\napp.lrl.lilly.com/compute\n:\nhybrid\nScheduling Workloads\n​\nDeployment Scheduled on Fargate in\nserverless\nNamespace\n​\nNote that\napp.lrl.lilly.com/compute: serverless\nmetadata.label for the Pod template\nis not required\nin this instance as it will be applied from the namespace configuration. Template for app running on fargate inside of a serverless namespace:\napiVersion\n:\napps/v1\nkind\n:\nDeployment\nmetadata\n:\nname\n:\nyour\n-\napp\nnamespace\n:\nyour\n-\napp\n-\nnamespace\n-\ndev\nspec\n:\nselector\n:\nmatchLabels\n:\napp.kubernetes.io/name\n:\nyour\n-\napp\ntemplate\n:\nmetadata\n:\nlabels\n:\napp.kubernetes.io/name\n:\nyour\n-\napp\nspec\n:\ncontainers\n:\n-\nimage\n:\n283234040926.dkr.ecr.us\n-\neast\n-\n2.amazonaws.com/lrl_new_app\n:\nsha\n-\na431842\n# {\"$imagepolicy\": \"<namespace-name>:<policy-name>\"}\nname\n:\nyour\n-\napp\nresources\n:\nlimits\n:\ncpu\n:\n1\nmemory\n:\n10G\nrequests\n:\ncpu\n:\n1\nmemory\n:\n10G\nDeployment Scheduled on Fargate in\nhybrid\nNamespace\n​\nNote that\napp.lrl.lilly.com/compute: serverless\nmetadata.label for the Pod template\nis required\nin this instance. Example application running on fargate within a hybrid namespace:\napiVersion\n:\napps/v1\nkind\n:\nDeployment\nmetadata\n:\nname\n:\nyour\n-\napp\nnamespace\n:\nyour\n-\napp\n-\nnamespace\n-\ndev\nspec\n:\nselector\n:\nmatchLabels\n:\napp.kubernetes.io/name\n:\nyour\n-\napp\ntemplate\n:\nmetadata\n:\nlabels\n:\napp.kubernetes.io/name\n:\nyour\n-\napp\napp.lrl.lilly.com/compute\n:\nserverless\nspec\n:\ncontainers\n:\n-\nimage\n:\n283234040926.dkr.ecr.us\n-\neast\n-\n2.amazonaws.com/lrl_new_app\n:\nsha\n-\na431842\n# {\"$imagepolicy\": \"<namespace-name>:<policy-name>\"}\nname\n:\nyour\n-\napp\nresources\n:\nlimits\n:\ncpu\n:\n1\nmemory\n:\n10G\nrequests\n:\ncpu\n:\n1\nmemory\n:\n10G\nDeployment Scheduled on Default EC2 in\nhybrid\nNamespace\n​\nNote that a combination of spec.nodeSelector and spec.tolerations for the Pod template is required for scheduling. Example application running on EC2 within a hybrid namespace:\napiVersion\n:\napps/v1\nkind\n:\nDeployment\nmetadata\n:\nname\n:\nyour\n-\napp\nnamespace\n:\nyour\n-\napp\n-\nnamespace\n-\ndev\nspec\n:\nselector\n:\nmatchLabels\n:\napp.kubernetes.io/name\n:\nyour\n-\napp\ntemplate\n:\nmetadata\n:\nlabels\n:\napp.kubernetes.io/name\n:\nyour\n-\napp\nspec\n:\ncontainers\n:\n-\nimage\n:\n283234040926.dkr.ecr.us\n-\neast\n-\n2.amazonaws.com/lrl_new_app\n:\nsha\n-\na431842\n# {\"$imagepolicy\": \"<namespace-name>:<policy-name>\"}\nname\n:\nyour\n-\napp\nresources\n:\nlimits\n:\ncpu\n:\n3\nmemory\n:\n40G\nrequests\n:\ncpu\n:\n3\nmemory\n:\n40G\nports\n:\n-\ncontainerPort\n:\n3838\n# Use node selector to specify the run environment (dev/qa/prd)\nnodeSelector\n:\napp.lrl.lilly.com/env\n:\ndev\ntolerations\n:\n-\nkey\n:\ndedicated\nvalue\n:\n\"ec2\"\neffect\n:\n\"NoExecute\"\nDeployment Scheduled on Default On-premise Connected EC2 in\nhybrid\nNamespace\n​\nNote that a combination of spec.nodeSelector and spec.tolerations for the Pod template is required for scheduling. Template for applications to follow in order to schedule nodes on the pre defined OnPrem node group:\napiVersion\n:\napps/v1\nkind\n:\nDeployment\nmetadata\n:\nname\n:\nyour\n-\napp\nnamespace\n:\nyour\n-\napp\n-\nnamespace\n-\ndev\nannotations\n:\napp.lilly.com/flux.automated\n:\n\"true\"\napp.lilly.com/flux.simple.<policy-name>\n:\n\"<aws-account-number>;<your-repo-name-in-ecr>;glob:<tag-pattern>\"\n# Example: app.lilly.com/flux.simple.docs-policy: \"283234040926;lrl_light_k8s_infra_apps_catsdocs;glob:sha-.*\"\nwave.pusher.com/update-on-config-change\n:\n\"true\"\nspec\n:\nselector\n:\nmatchLabels\n:\napp.kubernetes.io/name\n:\nyour\n-\napp\ntemplate\n:\nmetadata\n:\nlabels\n:\napp.kubernetes.io/name\n:\nyour\n-\napp\nspec\n:\ncontainers\n:\n-\nimage\n:\n283234040926.dkr.ecr.us\n-\neast\n-\n2.amazonaws.com/lrl_new_app\n:\nsha\n-\na431842\n# {\"$imagepolicy\": \"<namespace-name>:<policy-name>\"}\nname\n:\nyour\n-\napp\nresources\n:\nlimits\n:\ncpu\n:\n1\nmemory\n:\n10G\nrequests\n:\ncpu\n:\n1\nmemory\n:\n10G\nports\n:\n-\ncontainerPort\n:\n3838\nnodeSelector\n:\nnodeGroup\n:\nonPremise\napp.lrl.lilly.com/env\n:\ndev\ntolerations\n:\n-\nkey\n:\nnodeGroup\nvalue\n:\n\"onPremise\"\neffect\n:\nNoExecute\n-\nkey\n:\ndedicated\nvalue\n:\n\"ec2\"\neffect\n:\n\"NoExecute\"\nDeployment Scheduled on Custom Dedicated EC2 Instance\n​\nThe following template will help users select the an existing ASG dedicated instance for their application. Note that tolerations and node selectors will depend on the particular configuration of the autoscaling group.\napiVersion\n:\napps/v1\nkind\n:\nDeployment\nmetadata\n:\nname\n:\nyour\n-\napp\nnamespace\n:\nyour\n-\napp\n-\nnamespace\n-\ndev\nspec\n:\nselector\n:\nmatchLabels\n:\napp.kubernetes.io/name\n:\nyour\n-\napp\n-\nlabel\ntemplate\n:\nmetadata\n:\nlabels\n:\napp.kubernetes.io/name\n:\nyour\n-\napp\n-\nlabel\nspec\n:\ncontainers\n:\n-\nimage\n:\n283234040926.dkr.ecr.us\n-\neast\n-\n2.amazonaws.com/lrl_new_app\n:\nsha\n-\na431842\n# {\"$imagepolicy\": \"<namespace-name>:<policy-name>\"}\nname\n:\nyour\n-\napp\nresources\n:\nlimits\n:\ncpu\n:\n# Specify cpus, example: 2\nmemory\n:\n# Specify memory. example: 8G\nnvidia.com/gpu\n:\n# set this field to \"1\" if scheduling for gpus, else remove the field\nrequests\n:\ncpu\n:\n# Specify cpu. example: 2\nmemory\n:\n# Specify memory. example: 8G\nnvidia.com/gpu\n:\n# set this field to \"1\" if scheduling for gpus, else remove the field\nnodeSelector\n:\napp\n:\n[\nASG app name\n]\n(https\n:\n//github.com/EliLillyCo/LRL_light_k8s_infra/blob/main/aws/lib/stacks/eks\n-\nnodegroups.ts)\napp.lrl.lilly.com/env\n:\n[\nASG env\n,\ni.e. dev\n|\nqa\n|\nprd\n]\n(https\n:\n//github.com/EliLillyCo/LRL_light_k8s_infra/blob/main/aws/lib/stacks/eks\n-\nnodegroups.ts)\ntolerations\n:\n# <-- this will vary depending on the configuration of the ASG!\n-\nkey\n:\nnvidia.com/gpu\neffect\n:\nNoSchedule\n-\nkey\n:\ndedicated\nvalue\n:\n\"ec2\"\neffect\n:\n\"NoExecute\"\n-\nkey\n:\napp\nvalue\n:\n[\nASG taint name\n,\ntypically same as ASG app name\n]\n(https\n:\n//github.com/EliLillyCo/LRL_light_k8s_infra/blob/main/aws/lib/stacks/eks\n-\nnodegroups.ts)\neffect\n:\n\"NoExecute\"\nEdit this page\nPrevious\nIngress Patterns\nNext\nScaling\nServices that Schedule Workloads\nFargate (planned for obsolescence in 2025)\nEC2 Autoscaling Groups and Managed EKS NodeGroups\nAWS Karpenter\nNode Networking Configurations\nOn-premise Network Connected Nodes\nConfiguration Options\nConfigure Workload Scheduling via Namespace Annotation\nAffinities, Selectors, Tolerations, and Topologies, \"Oh My!\"\nExamples\nKarpenter\nNamespace Configuration\nFargate Only Namespace (\nserverless\nnamespace)\nEC2 or Fargate Namespace (\nhybrid\nnamespace)\nScheduling Workloads\nDeployment Scheduled on Fargate in\nserverless\nNamespace\nDeployment Scheduled on Fargate in\nhybrid\nNamespace\nDeployment Scheduled on Default EC2 in\nhybrid\nNamespace\nDeployment Scheduled on Default On-premise Connected EC2 in\nhybrid\nNamespace\nDeployment Scheduled on Custom Dedicated EC2 Instance\nLilly SPE Research Technology and Platforms",
  "links_found": 1,
  "depth": 4,
  "crawled_at": "2026-03-20T15:01:56.891091",
  "pagination_items": [
    {
      "tab": "default",
      "content": {
        "title": "Compute and Workload Scheduling",
        "description": "There are three types of provisioned nodes supported by the platform:",
        "links": [
          "/",
          "#services-that-schedule-workloads",
          "#fargate-planned-for-obsolescence-in-2025",
          "https://docs.aws.amazon.com/eks/latest/userguide/fargate-pod-configuration.html",
          "#ec2-autoscaling-groups-and-managed-eks-nodegroups",
          "https://github.com/EliLillyCo/LRL_light_k8s_infra/blob/main/aws/lib/stacks/eks-fargate.ts",
          "#aws-karpenter",
          "/guide/Karpenter",
          "#node-networking-configurations",
          "#on-premise-network-connected-nodes",
          "/guide/Namespace#2-annotations-explained",
          "/guide/Namespace#security-group-rule",
          "#configuration-options",
          "#configure-workload-scheduling-via-namespace-annotation",
          "#affinities-selectors-tolerations-and-topologies-oh-my",
          "https://kubernetes.io/docs/concepts/scheduling-eviction/assign-pod-node/",
          "https://kubernetes.io/docs/concepts/scheduling-eviction/taint-and-toleration/",
          "#examples",
          "#karpenter",
          "#deployment-scheduled-on-general-purpose-node",
          "#deployment-scheduled-on-accelerated-gpu-enabled-node",
          "#namespace-configuration",
          "#fargate-only-namespace-serverless-namespace",
          "#ec2-or-fargate-namespace-hybrid-namespace",
          "#scheduling-workloads",
          "#deployment-scheduled-on-fargate-in-serverless-namespace",
          "#deployment-scheduled-on-fargate-in-hybrid-namespace",
          "#deployment-scheduled-on-default-ec2-in-hybrid-namespace",
          "#deployment-scheduled-on-default-on-premise-connected-ec2-in-hybrid-namespace",
          "#deployment-scheduled-on-custom-dedicated-ec2-instance",
          "https://github.com/EliLillyCo/LRL_light_k8s_infra_apps_docs/tree/main/docs/guide/ComputeAndWorkloadScheduling.md"
        ]
      }
    }
  ],
  "pagination_count": 1
}